consolepy/__init__.py
consolepy/cli.py
consolepy/core.py
consolepy/styles.py
consolepy/utils.py
consoleprintpy-0.1.4.dist-info/METADATA
consoleprintpy-0.1.4.dist-info/WHEEL
consoleprintpy-0.1.4.dist-info/entry_points.txt
consoleprintpy-0.1.4.dist-info/top_level.txt
consoleprintpy-0.1.4.dist-info/RECORD
