Metadata-Version: 2.4
Name: consoleprintpy
Version: 0.1.4
Summary: JS-like console logging for Python with colors and styles
Author: Yurigabriel6
License-Expression: MIT
Requires-Python: >=3.8
